<?xml version="1.0" encoding="UTF-8"?>
<objects serializationModel="Studio.02.02.00">
	<object class="AudioFile" id="{11515c7e-06a3-406a-bb23-15ae237fa490}">
		<property name="assetPath">
			<value>VO_NoAmmo_03.wav</value>
		</property>
		<property name="frequencyInKHz">
			<value>44.0999985</value>
		</property>
		<property name="channelCount">
			<value>2</value>
		</property>
		<property name="length">
			<value>1.45718820861678</value>
		</property>
		<relationship name="masterAssetFolder">
			<destination>{c6ca15b6-bb30-4948-b2f1-4104766060fe}</destination>
		</relationship>
	</object>
</objects>
